LICENSE
MANIFEST.in
README.rst
setup.py
nose_watch.egg-info/PKG-INFO
nose_watch.egg-info/SOURCES.txt
nose_watch.egg-info/dependency_links.txt
nose_watch.egg-info/entry_points.txt
nose_watch.egg-info/requires.txt
nose_watch.egg-info/top_level.txt
nosewatch/__init__.py
nosewatch/plugin.py
tests/__init__.py
tests/test_plugin.py