Metadata-Version: 1.1
Name: nose-watch
Version: 0.9.2
Summary: A nose plugin that re-runs test suite on filesystem event.
Home-page: https://github.com/lukaszb/nose-watch
Author: Lukasz Balcerzak
Author-email: lukaszbalcerzak@gmail.com
License: UNKNOWN
Platform: UNKNOWN
Classifier: Development Status :: 4 - Beta
Classifier: Intended Audience :: Developers
Classifier: License :: OSI Approved :: MIT License
Classifier: Programming Language :: Python :: 2
Classifier: Programming Language :: Python :: 2.6
Classifier: Programming Language :: Python :: 2.7
Classifier: Programming Language :: Python :: 3
Classifier: Programming Language :: Python :: 3.3
Classifier: Programming Language :: Python :: 3.4
Classifier: Programming Language :: Python :: 3.5
Classifier: Programming Language :: Python :: 3.6
Classifier: Topic :: Software Development :: Testing
